{
  "venue": {
    "city": {
      "name": "Elche"
    },
    "venueCoordinates": {
      "latitude": 38.267044,
      "longitude": -0.663305
    },
    "hidden": false,
    "slug": "estadio-mart-nez-valero",
    "name": "Estadio Martínez Valero",
    "capacity": 31388,
    "mainTeams": [
      {
        "name": "Elche",
        "slug": "elche",
        "shortName": "Elche",
        "gender": "M",
        "sport": {
          "name": "Football",
          "slug": "football",
          "id": 1
        },
        "userCount": 100116,
        "nameCode": "ELC",
        "disabled": false,
        "national": false,
        "type": 0,
        "id": 2846,
        "teamColors": {
          "primary": "#ffffff",
          "secondary": "#336600",
          "text": "#336600"
        },
        "fieldTranslations": {
          "nameTranslation": {
            "ar": "إلتشي",
            "bn": "এলচে",
            "hi": "एल्चे",
            "ru": "Эльче"
          },
          "shortNameTranslation": {}
        }
      }
    ],
    "country": {
      "alpha2": "ES",
      "name": "Spain",
      "slug": "spain"
    },
    "id": 1042,
    "fieldTranslations": {
      "nameTranslation": {
        "ar": "ملعب مارتينيز فاليرو",
        "hi": "एस्टेडियो मार्टिनेज वलेरो",
        "bn": "এস্তাদিও মার্টিনেজ ভ্যালেরো"
      },
      "shortNameTranslation": {}
    },
    "stadium": {
      "name": "Estadio Martínez Valero",
      "capacity": 31388
    },
    "openedAtTimestamp": 210988800
  },
  "statistics": {
    "totalMatches": 289,
    "homeTeamGoalsScored": 379,
    "awayTeamGoalsScored": 303,
    "avgRedCardsPerGame": 0.29757785467128,
    "avgCornerKicksPerGame": 14.937716262976,
    "homeTeamWinsPercentage": 40.484429065744,
    "awayTeamWinsPercentage": 26.989619377163,
    "drawsPercentage": 30.449826989619
  }
}