{"matchInfo": {"id": "288lesgslzcbljs163839jl04", "coverageLevel": "13", "date": "2026-02-01Z", "time": "20:00:00Z", "localDate": "2026-02-01", "localTime": "21:00:00", "week": "22", "postMatch": "1", "numberOfPeriods": 2, "periodLength": 45, "var": "1", "lastUpdated": "2026-02-23T05:31:31Z", "description": "Athletic Club vs Real Sociedad", "sport": {"id": "289u5typ3vp4ifwh5thalohmq", "name": "Soccer"}, "ruleset": {"id": "79plas4983031idr6vw83nuel", "name": "Men"}, "competition": {"id": "34pl8szyvrbwcmfkuocjm3r6t", "name": "Primera División", "knownName": "Spanish La Liga", "sponsorName": "LALIGA EA SPORTS", "competitionCode": "PRD", "competitionFormat": "Domestic league", "country": {"id": "49ih1pwv3ahshdf8uzrimi54c", "name": "Spain"}}, "tournamentCalendar": {"id": "80zg2v1cuqcfhphn56u4qpyqc", "startDate": "2025-08-15Z", "endDate": "2026-05-24Z", "name": "2025/2026"}, "stage": {"id": "81qyu4gx74q5nzfd3gi2gy51w", "formatId": "e2q01r9o9jwiq1fls93d1sslx", "startDate": "2025-08-15Z", "endDate": "2026-05-24Z", "name": "Regular Season"}, "contestant": [{"id": "3czravw89omgc9o4s0w3l1bg5", "name": "Athletic Club", "shortName": "Athletic", "officialName": "Athletic Club", "code": "ATH", "position": "home", "country": {"id": "49ih1pwv3ahshdf8uzrimi54c", "name": "Spain"}}, {"id": "63f5h8t5e9qm1fqmvfkb23ghh", "name": "Real Sociedad", "shortName": "Real Sociedad", "officialName": "Real Sociedad de Fútbol", "code": "RSO", "position": "away", "country": {"id": "49ih1pwv3ahshdf8uzrimi54c", "name": "Spain"}}], "venue": {"id": "3tsyaiz1y1gg31xw81qgtrx4w", "neutral": "no", "longName": "Estadio de San Mamés", "shortName": "Estadio de San Mamés", "latitude": "43.264172789", "longitude": "-2.949383125"}}, "liveData": {"matchDetails": {"periodId": 14, "matchStatus": "Played", "winner": "draw", "matchLengthMin": 98, "matchLengthSec": 14, "period": [{"id": 1, "start": "2026-02-01T20:01:58Z", "end": "2026-02-01T20:50:04Z", "lengthMin": 48, "lengthSec": 6, "announcedInjuryTime": 180}, {"id": 2, "start": "2026-02-01T21:06:28Z", "end": "2026-02-01T21:56:36Z", "lengthMin": 50, "lengthSec": 8, "announcedInjuryTime": 300}], "scores": {"ht": {"home": 0, "away": 1}, "ft": {"home": 1, "away": 1}, "total": {"home": 1, "away": 1}}}, "goal": [{"contestantId": "63f5h8t5e9qm1fqmvfkb23ghh", "periodId": 1, "timeMin": 37, "timeMinSec": "36:47", "lastUpdated": "2026-02-01T20:39:30Z", "timestamp": "2026-02-01T20:38:46Z", "type": "G", "scorerId": "7pmigpf4yfi6dfih8e1ogdwb9", "scorerName": "Gonçalo Guedes", "assistPlayerId": "d4tdx2ctadv6kc3tbq4as8bmx", "assistPlayerName": "Sergio Gómez", "optaEventId": "2895649885", "homeScore": 0, "awayScore": 1}, {"contestantId": "3czravw89omgc9o4s0w3l1bg5", "periodId": 2, "timeMin": 88, "timeMinSec": "87:15", "lastUpdated": "2026-02-01T21:49:32Z", "timestamp": "2026-02-01T21:48:44Z", "type": "G", "scorerId": "7ubtan6a51o79w469zawrqqqd", "scorerName": "Íñigo Ruíz de Galarreta", "assistPlayerId": "8hm6d6395johhjsoe8jz6dcyd", "assistPlayerName": "Yuri", "optaEventId": "2895679995", "homeScore": 1, "awayScore": 1}], "card": [{"contestantId": "63f5h8t5e9qm1fqmvfkb23ghh", "periodId": 1, "timeMin": 23, "timeMinSec": "22:38", "lastUpdated": "2026-02-01T20:24:45Z", "timestamp": "2026-02-01T20:24:36Z", "type": "YC", "playerId": "48gjuou5eashpj8wbwd18iju1", "playerName": "Igor Zubeldia", "optaEventId": "2895641709", "cardReason": "Foul"}, {"contestantId": "63f5h8t5e9qm1fqmvfkb23ghh", "periodId": 2, "timeMin": 51, "timeMinSec": "50:13", "lastUpdated": "2026-02-01T21:12:07Z", "timestamp": "2026-02-01T21:11:42Z", "type": "YC", "playerId": "8krgbfnydbtyongkwnsaj43kk", "playerName": "Jon Martín", "optaEventId": "2895663981", "cardReason": "Dissent"}, {"contestantId": "3czravw89omgc9o4s0w3l1bg5", "periodId": 2, "timeMin": 56, "timeMinSec": "55:59", "lastUpdated": "2026-02-01T21:18:02Z", "timestamp": "2026-02-01T21:17:27Z", "type": "YC", "playerId": "8hm6d6395johhjsoe8jz6dcyd", "playerName": "Yuri", "optaEventId": "2895667055", "cardReason": "Foul"}, {"contestantId": "3czravw89omgc9o4s0w3l1bg5", "periodId": 2, "timeMin": 69, "timeMinSec": "68:26", "lastUpdated": "2026-02-01T21:30:10Z", "timestamp": "2026-02-01T21:29:54Z", "type": "YC", "playerId": "7r7wgbcu7vmlj19m9jpjhu1yi", "playerName": "Jesús Areso", "optaEventId": "2895672167", "cardReason": "Handball"}, {"contestantId": "3czravw89omgc9o4s0w3l1bg5", "periodId": 2, "timeMin": 75, "timeMinSec": "74:42", "lastUpdated": "2026-02-01T21:36:37Z", "timestamp": "2026-02-01T21:36:10Z", "type": "YC", "playerId": "43sv2qpco7dsobxna7z9dugyy", "playerName": "Urko Izeta", "optaEventId": "2895674891", "cardReason": "Foul"}, {"contestantId": "63f5h8t5e9qm1fqmvfkb23ghh", "periodId": 2, "timeMin": 83, "timeMinSec": "82:27", "lastUpdated": "2026-02-01T21:44:08Z", "timestamp": "2026-02-01T21:43:55Z", "type": "RC", "playerId": "dvrk8qmt9ta4c3kvjgsad7t91", "playerName": "Brais Méndez", "optaEventId": "2895678267", "cardReason": "Violent Conduct"}, {"contestantId": "3czravw89omgc9o4s0w3l1bg5", "periodId": 2, "timeMin": 84, "timeMinSec": "83:13", "lastUpdated": "2026-02-01T21:44:50Z", "timestamp": "2026-02-01T21:44:41Z", "type": "YC", "playerId": "5kd57453a90zahgdxwkghr816", "playerName": "Aitor Paredes", "optaEventId": "2895678487", "cardReason": "Argument"}], "substitute": [{"contestantId": "3czravw89omgc9o4s0w3l1bg5", "periodId": 2, "timeMin": 46, "timeMinSec": "45:00", "lastUpdated": "2026-02-01T21:06:16Z", "timestamp": "2026-02-01T21:06:09Z", "playerOnId": "7ubtan6a51o79w469zawrqqqd", "playerOnName": "Íñigo Ruíz de Galarreta", "playerOffId": "1xsrdgt40nb6p9qvt6mf272fo", "playerOffName": "Alejandro Rego", "subReason": "Tactical"}, {"contestantId": "3czravw89omgc9o4s0w3l1bg5", "periodId": 2, "timeMin": 62, "timeMinSec": "61:54", "lastUpdated": "2026-02-01T21:23:28Z", "timestamp": "2026-02-01T21:23:22Z", "playerOnId": "7aoe0u87gxgv9tvgrotcfue7e", "playerOnName": "Robert Navarro", "playerOffId": "b2rqgjegzeyq6wy6qu63zz2fo", "playerOffName": "Unai Gómez", "subReason": "Tactical"}, {"contestantId": "63f5h8t5e9qm1fqmvfkb23ghh", "periodId": 2, "timeMin": 63, "timeMinSec": "62:04", "lastUpdated": "2026-02-01T21:23:37Z", "timestamp": "2026-02-01T21:23:33Z", "playerOnId": "dvrk8qmt9ta4c3kvjgsad7t91", "playerOnName": "Brais Méndez", "playerOffId": "9x5uo2wkxp9fk1arygbkl6u0a", "playerOffName": "L. Sučić", "subReason": "Tactical"}, {"contestantId": "63f5h8t5e9qm1fqmvfkb23ghh", "periodId": 2, "timeMin": 63, "timeMinSec": "62:08", "lastUpdated": "2026-02-01T21:23:43Z", "timestamp": "2026-02-01T21:23:37Z", "playerOnId": "et849xmcdgsy5itb8i4w7qkq2", "playerOnName": "Beñat Turrientes", "playerOffId": "706la37b8u3v3n6mqtbjs73mc", "playerOffName": "Jon Gorrotxategi", "subReason": "Tactical"}, {"contestantId": "3czravw89omgc9o4s0w3l1bg5", "periodId": 2, "timeMin": 72, "timeMinSec": "71:25", "lastUpdated": "2026-02-01T21:33:00Z", "timestamp": "2026-02-01T21:32:54Z", "playerOnId": "ddvvwqxpsqqboupi3gx1ijhed", "playerOnName": "I. Williams", "playerOffId": "66jotyvbhtz5cjvhbby6luelm", "playerOffName": "Nico Williams", "subReason": "Tactical"}, {"contestantId": "3czravw89omgc9o4s0w3l1bg5", "periodId": 2, "timeMin": 72, "timeMinSec": "71:30", "lastUpdated": "2026-02-01T21:33:06Z", "timestamp": "2026-02-01T21:32:58Z", "playerOnId": "43sv2qpco7dsobxna7z9dugyy", "playerOnName": "Urko Izeta", "playerOffId": "do5tibysnhbnbw18nwdo39kut", "playerOffName": "Alex Berenguer", "subReason": "Tactical"}, {"contestantId": "63f5h8t5e9qm1fqmvfkb23ghh", "periodId": 2, "timeMin": 77, "timeMinSec": "76:29", "lastUpdated": "2026-02-01T21:38:05Z", "timestamp": "2026-02-01T21:37:57Z", "playerOnId": "a5sz66h4t5kg1umvtth785jis", "playerOnName": "Wesley", "playerOffId": "7pmigpf4yfi6dfih8e1ogdwb9", "playerOffName": "Gonçalo Guedes", "subReason": "Tactical"}, {"contestantId": "63f5h8t5e9qm1fqmvfkb23ghh", "periodId": 2, "timeMin": 77, "timeMinSec": "76:51", "lastUpdated": "2026-02-01T21:38:27Z", "timestamp": "2026-02-01T21:38:19Z", "playerOnId": "euur9yvhgrieu4kl0vdkh244q", "playerOnName": "O. Óskarsson", "playerOffId": "b45ryclny991bm7qosieyg1cl", "playerOffName": "Mikel Oyarzabal", "subReason": "Tactical"}, {"contestantId": "3czravw89omgc9o4s0w3l1bg5", "periodId": 2, "timeMin": 79, "timeMinSec": "78:25", "lastUpdated": "2026-02-01T21:40:15Z", "timestamp": "2026-02-01T21:39:54Z", "playerOnId": "b91n9sdabth8oocdawayybdud", "playerOnName": "Andoni Gorosabel", "playerOffId": "7r7wgbcu7vmlj19m9jpjhu1yi", "playerOffName": "Jesús Areso", "subReason": "Tactical"}, {"contestantId": "63f5h8t5e9qm1fqmvfkb23ghh", "periodId": 2, "timeMin": 85, "timeMinSec": "84:33", "lastUpdated": "2026-02-01T21:46:09Z", "timestamp": "2026-02-01T21:46:01Z", "playerOnId": "bj929w5yi7lnz36jxsi5qnq7e", "playerOnName": "Aihen Muñoz", "playerOffId": "aka2yqxmqpioxc1qzkl62ejv8", "playerOffName": "Pablo Marín", "subReason": "Tactical"}], "lineUp": [{"contestantId": "3czravw89omgc9o4s0w3l1bg5", "formationUsed": "4231", "averageAge": 26.5, "player": [{"playerId": "4vlurpsi44g09g159t61u83bp", "firstName": "Unai", "lastName": "Simón Mendibil", "shortFirstName": "Unai", "shortLastName": "Simón", "matchName": "Unai Simón", "shirtNumber": 1, "position": "Goalkeeper", "positionSide": "Centre", "formationPlace": "1", "stat": [{"type": "accuratePass", "value": "27"}, {"type": "gameStarted", "value": "1"}, {"type": "goalKicks", "value": "4"}, {"type": "goalsConceded", "value": "1"}, {"type": "lostCorners", "value": "1"}, {"type": "minsPlayed", "value": "90"}, {"type": "saves", "value": "4"}, {"type": "totalClearance", "value": "1"}, {"type": "totalPass", "value": "45"}, {"type": "formationPlace", "value": "1"}]}, {"playerId": "5ayo0fp6wod7cqg71e38zdz4k", "firstName": "Adama", "lastName": "Boiro Boiro", "shortFirstName": "Adama", "shortLastName": "Boiro", "matchName": "Adama Boiro", "shirtNumber": 19, "position": "Defender", "positionSide": "Left", "formationPlace": "3", "stat": [{"type": "accuratePass", "value": "32"}, {"type": "blockedScoringAtt", "value": "1"}, {"type": "gameStarted", "value": "1"}, {"type": "goalsConceded", "value": "1"}, {"type": "lostCorners", "value": "1"}, {"type": "minsPlayed", "value": "90"}, {"type": "totalClearance", "value": "2"}, {"type": "totalPass", "value": "37"}, {"type": "totalScoringAtt", "value": "1"}, {"type": "totalThrows", "value": "13"}, {"type": "wonCorners", "value": "2"}, {"type": "formationPlace", "value": "3"}]}, {"playerId": "8hm6d6395johhjsoe8jz6dcyd", "firstName": "Yuri", "lastName": "Berchiche Izeta", "shortFirstName": "Yuri", "shortLastName": "Berchiche", "matchName": "Yuri", "shirtNumber": 17, "position": "Defender", "positionSide": "Left/Centre", "formationPlace": "6", "captain": "yes", "stat": [{"type": "accuratePass", "value": "53"}, {"type": "fouls", "value": "2"}, {"type": "gameStarted", "value": "1"}, {"type": "goalAssist", "value": "1"}, {"type": "goalsConceded", "value": "1"}, {"type": "minsPlayed", "value": "90"}, {"type": "totalClearance", "value": "1"}, {"type": "totalOffside", "value": "1"}, {"type": "totalPass", "value": "56"}, {"type": "yellowCard", "value": "1"}, {"type": "formationPlace", "value": "6"}]}, {"playerId": "5kd57453a90zahgdxwkghr816", "firstName": "Aitor", "lastName": "Paredes Casamichana", "shortFirstName": "Aitor", "shortLastName": "Paredes", "matchName": "Aitor Paredes", "shirtNumber": 4, "position": "Defender", "positionSide": "Centre/Right", "formationPlace": "5", "stat": [{"type": "accuratePass", "value": "43"}, {"type": "blockedScoringAtt", "value": "1"}, {"type": "fouls", "value": "2"}, {"type": "gameStarted", "value": "1"}, {"type": "goalsConceded", "value": "1"}, {"type": "minsPlayed", "value": "90"}, {"type": "ontargetScoringAtt", "value": "1"}, {"type": "shotOffTarget", "value": "1"}, {"type": "totalClearance", "value": "3"}, {"type": "totalPass", "value": "49"}, {"type": "totalScoringAtt", "value": "3"}, {"type": "totalTackle", "value": "1"}, {"type": "wonCorners", "value": "1"}, {"type": "wonTackle", "value": "1"}, {"type": "yellowCard", "value": "1"}, {"type": "formationPlace", "value": "5"}]}, {"playerId": "7r7wgbcu7vmlj19m9jpjhu1yi", "firstName": "Jesús", "lastName": "Areso Blanco", "shortFirstName": "Jesús", "shortLastName": "Areso", "matchName": "Jesús Areso", "shirtNumber": 12, "position": "Defender", "positionSide": "Right", "formationPlace": "2", "stat": [{"type": "accuratePass", "value": "17"}, {"type": "fouls", "value": "1"}, {"type": "gameStarted", "value": "1"}, {"type": "goalsConceded", "value": "1"}, {"type": "minsPlayed", "value": "79"}, {"type": "totalClearance", "value": "3"}, {"type": "totalPass", "value": "21"}, {"type": "totalSubOff", "value": "1"}, {"type": "totalTackle", "value": "3"}, {"type": "totalThrows", "value": "5"}, {"type": "wasFouled", "value": "1"}, {"type": "yellowCard", "value": "1"}, {"type": "formationPlace", "value": "2"}]}, {"playerId": "1xsrdgt40nb6p9qvt6mf272fo", "firstName": "Alejandro", "lastName": "Rego Mora", "shortFirstName": "Alejandro", "shortLastName": "Rego", "matchName": "Alejandro Rego", "shirtNumber": 30, "position": "Defensive Midfielder", "positionSide": "Left/Centre", "formationPlace": "4", "stat": [{"type": "accuratePass", "value": "17"}, {"type": "blockedScoringAtt", "value": "1"}, {"type": "fouls", "value": "1"}, {"type": "gameStarted", "value": "1"}, {"type": "goalsConceded", "value": "1"}, {"type": "minsPlayed", "value": "45"}, {"type": "totalClearance", "value": "1"}, {"type": "totalPass", "value": "20"}, {"type": "totalScoringAtt", "value": "1"}, {"type": "totalSubOff", "value": "1"}, {"type": "totalTackle", "value": "2"}, {"type": "formationPlace", "value": "4"}]}, {"playerId": "ck7lu09geq8mi6vkf2llyi5ii", "firstName": "Mikel", "lastName": "Jauregizar Alboniga", "shortFirstName": "Mikel", "shortLastName": "Jauregizar", "matchName": "Mikel Jauregizar", "shirtNumber": 18, "position": "Defensive Midfielder", "positionSide": "Centre/Right", "formationPlace": "8", "stat": [{"type": "accuratePass", "value": "37"}, {"type": "blockedScoringAtt", "value": "1"}, {"type": "fouls", "value": "3"}, {"type": "gameStarted", "value": "1"}, {"type": "goalsConceded", "value": "1"}, {"type": "minsPlayed", "value": "90"}, {"type": "shotOffTarget", "value": "1"}, {"type": "totalClearance", "value": "1"}, {"type": "totalPass", "value": "48"}, {"type": "totalScoringAtt", "value": "2"}, {"type": "totalTackle", "value": "2"}, {"type": "wonCorners", "value": "1"}, {"type": "wonTackle", "value": "2"}, {"type": "formationPlace", "value": "8"}]}, {"playerId": "66jotyvbhtz5cjvhbby6luelm", "firstName": "Nicholas", "lastName": "Williams Arthuer", "shortFirstName": "Nico", "shortLastName": "Williams", "knownName": "Nico Williams", "matchName": "Nico Williams", "shirtNumber": 10, "position": "Attacking Midfielder", "positionSide": "Left", "formationPlace": "11", "stat": [{"type": "accuratePass", "value": "14"}, {"type": "blockedScoringAtt", "value": "3"}, {"type": "gameStarted", "value": "1"}, {"type": "goalsConceded", "value": "1"}, {"type": "minsPlayed", "value": "72"}, {"type": "totalOffside", "value": "1"}, {"type": "totalPass", "value": "25"}, {"type": "totalScoringAtt", "value": "3"}, {"type": "totalSubOff", "value": "1"}, {"type": "totalTackle", "value": "1"}, {"type": "totalThrows", "value": "2"}, {"type": "wasFouled", "value": "2"}, {"type": "wonCorners", "value": "1"}, {"type": "formationPlace", "value": "11"}]}, {"playerId": "b2rqgjegzeyq6wy6qu63zz2fo", "firstName": "Unai", "lastName": "Gómez Etxebarria", "shortFirstName": "Unai", "shortLastName": "Gómez", "matchName": "Unai Gómez", "shirtNumber": 20, "position": "Attacking Midfielder", "positionSide": "Centre", "formationPlace": "10", "stat": [{"type": "accuratePass", "value": "10"}, {"type": "gameStarted", "value": "1"}, {"type": "goalsConceded", "value": "1"}, {"type": "minsPlayed", "value": "62"}, {"type": "shotOffTarget", "value": "1"}, {"type": "totalPass", "value": "14"}, {"type": "totalScoringAtt", "value": "1"}, {"type": "totalSubOff", "value": "1"}, {"type": "wonCorners", "value": "1"}, {"type": "formationPlace", "value": "10"}]}, {"playerId": "do5tibysnhbnbw18nwdo39kut", "firstName": "Alejandro", "lastName": "Berenguer Remiro", "shortFirstName": "Alex", "shortLastName": "Berenguer", "matchName": "Alex Berenguer", "shirtNumber": 7, "position": "Attacking Midfielder", "positionSide": "Right", "formationPlace": "7", "stat": [{"type": "accuratePass", "value": "15"}, {"type": "cornerTaken", "value": "5"}, {"type": "fouls", "value": "1"}, {"type": "gameStarted", "value": "1"}, {"type": "goalsConceded", "value": "1"}, {"type": "lostCorners", "value": "1"}, {"type": "minsPlayed", "value": "72"}, {"type": "ontargetScoringAtt", "value": "1"}, {"type": "shotOffTarget", "value": "2"}, {"type": "totalPass", "value": "18"}, {"type": "totalScoringAtt", "value": "3"}, {"type": "totalSubOff", "value": "1"}, {"type": "wasFouled", "value": "2"}, {"type": "formationPlace", "value": "7"}]}, {"playerId": "3tzvbdszdrj1tayik9igbve8l", "firstName": "Gorka", "lastName": "Guruzeta Rodríguez", "shortFirstName": "Gorka", "shortLastName": "Guruzeta", "matchName": "Gorka Guruzeta", "shirtNumber": 11, "position": "Striker", "positionSide": "Centre", "formationPlace": "9", "stat": [{"type": "accuratePass", "value": "11"}, {"type": "blockedScoringAtt", "value": "1"}, {"type": "fouls", "value": "1"}, {"type": "gameStarted", "value": "1"}, {"type": "goalsConceded", "value": "1"}, {"type": "minsPlayed", "value": "90"}, {"type": "ontargetScoringAtt", "value": "1"}, {"type": "totalPass", "value": "17"}, {"type": "totalScoringAtt", "value": "2"}, {"type": "totalTackle", "value": "1"}, {"type": "wasFouled", "value": "4"}, {"type": "formationPlace", "value": "9"}]}, {"playerId": "b91n9sdabth8oocdawayybdud", "firstName": "Andoni", "lastName": "Gorosabel Espinosa", "shortFirstName": "Andoni", "shortLastName": "Gorosabel", "matchName": "Andoni Gorosabel", "shirtNumber": 2, "position": "Substitute", "subPosition": "Defender", "stat": [{"type": "accuratePass", "value": "4"}, {"type": "minsPlayed", "value": "11"}, {"type": "totalClearance", "value": "1"}, {"type": "totalPass", "value": "5"}, {"type": "totalSubOn", "value": "1"}, {"type": "totalThrows", "value": "1"}, {"type": "wasFouled", "value": "1"}, {"type": "formationPlace", "value": "0"}]}, {"playerId": "a2k7c99py1zab3qa0i0pjy590", "firstName": "Asier", "lastName": "Hierro Campo", "shortFirstName": "Asier", "shortLastName": "Hierro", "matchName": "Asier Hierro", "shirtNumber": 31, "position": "Substitute", "subPosition": "Attacker", "stat": [{"type": "formationPlace", "value": "0"}]}, {"playerId": "43sv2qpco7dsobxna7z9dugyy", "firstName": "Urko", "lastName": "Iruretagoiena Lertxundi", "shortFirstName": "Urko", "shortLastName": "Iruretagoiena Lertxundi", "knownName": "Urko Izeta", "matchName": "Urko Izeta", "shirtNumber": 25, "position": "Substitute", "subPosition": "Attacker", "stat": [{"type": "accuratePass", "value": "3"}, {"type": "fouls", "value": "1"}, {"type": "minsPlayed", "value": "18"}, {"type": "shotOffTarget", "value": "1"}, {"type": "totalPass", "value": "4"}, {"type": "totalScoringAtt", "value": "1"}, {"type": "totalSubOn", "value": "1"}, {"type": "yellowCard", "value": "1"}, {"type": "formationPlace", "value": "0"}]}, {"playerId": "ey2uutfzsevzuvnsarwuny6tw", "firstName": "Iker", "lastName": "Monreal Agundez", "shortFirstName": "Iker", "shortLastName": "Monreal", "matchName": "Iker Monreal", "shirtNumber": 47, "position": "Substitute", "subPosition": "Defender", "stat": [{"type": "formationPlace", "value": "0"}]}, {"playerId": "7aoe0u87gxgv9tvgrotcfue7e", "firstName": "Roberto", "lastName": "Navarro Muñoz", "shortFirstName": "Robert", "shortLastName": "Navarro", "matchName": "Robert Navarro", "shirtNumber": 23, "position": "Substitute", "subPosition": "Midfielder", "stat": [{"type": "accuratePass", "value": "13"}, {"type": "cornerTaken", "value": "1"}, {"type": "fouls", "value": "1"}, {"type": "minsPlayed", "value": "28"}, {"type": "totalOffside", "value": "1"}, {"type": "totalPass", "value": "16"}, {"type": "totalSubOn", "value": "1"}, {"type": "totalTackle", "value": "1"}, {"type": "totalThrows", "value": "1"}, {"type": "wonTackle", "value": "1"}, {"type": "formationPlace", "value": "0"}]}, {"playerId": "b9q69u0q11bjpu0393sdy50", "firstName": "Alejandro", "lastName": "Padilla Pérez", "shortFirstName": "Álex", "shortLastName": "Padilla", "matchName": "Á. Padilla", "shirtNumber": 27, "position": "Substitute", "subPosition": "Goalkeeper", "stat": [{"type": "formationPlace", "value": "0"}]}, {"playerId": "7ubtan6a51o79w469zawrqqqd", "firstName": "Íñigo", "lastName": "Ruíz de Galarreta Etxeberria", "shortFirstName": "Íñigo", "shortLastName": "Ruíz de Galarreta", "matchName": "Íñigo Ruíz de Galarreta", "shirtNumber": 16, "position": "Substitute", "subPosition": "Midfielder", "stat": [{"type": "accuratePass", "value": "33"}, {"type": "blockedScoringAtt", "value": "1"}, {"type": "goals", "value": "1"}, {"type": "minsPlayed", "value": "45"}, {"type": "ontargetScoringAtt", "value": "1"}, {"type": "totalPass", "value": "41"}, {"type": "totalScoringAtt", "value": "2"}, {"type": "totalSubOn", "value": "1"}, {"type": "totalTackle", "value": "2"}, {"type": "totalThrows", "value": "1"}, {"type": "wasFouled", "value": "2"}, {"type": "wonTackle", "value": "2"}, {"type": "formationPlace", "value": "0"}]}, {"playerId": "26wj6flfqi59vgz6vwjgur2ay", "firstName": "Nicolás", "lastName": "Serrano Galdeano", "shortFirstName": "Nico", "shortLastName": "Serrano", "matchName": "Nico Serrano", "shirtNumber": 22, "position": "Substitute", "subPosition": "Attacker", "stat": [{"type": "formationPlace", "value": "0"}]}, {"playerId": "esru3us4k7xaj6hjycz78pdsk", "firstName": "Selton Sued", "lastName": "Sánchez Camilo", "shortFirstName": "Selton", "shortLastName": "Sánchez", "knownName": "Selton Sánchez", "matchName": "Selton Sánchez", "shirtNumber": 44, "position": "Substitute", "subPosition": "Midfielder", "stat": [{"type": "formationPlace", "value": "0"}]}, {"playerId": "83n1qv6ypl625aolzjeqifv11", "firstName": "Mikel", "lastName": "Vesga Arruti", "shortFirstName": "Mikel", "shortLastName": "Vesga", "matchName": "Mikel Vesga", "shirtNumber": 6, "position": "Substitute", "subPosition": "Midfielder", "stat": [{"type": "formationPlace", "value": "0"}]}, {"playerId": "ddvvwqxpsqqboupi3gx1ijhed", "firstName": "Iñaki", "lastName": "Williams Arthuer", "shortFirstName": "Iñaki", "shortLastName": "Williams", "knownName": "Iñaki Williams", "matchName": "I. Williams", "shirtNumber": 9, "position": "Substitute", "subPosition": "Attacker", "stat": [{"type": "accuratePass", "value": "4"}, {"type": "fouls", "value": "1"}, {"type": "minsPlayed", "value": "18"}, {"type": "totalPass", "value": "5"}, {"type": "totalSubOn", "value": "1"}, {"type": "formationPlace", "value": "0"}]}], "teamOfficial": [{"id": "dbdq6fyl44p43la2s5q9suehh", "firstName": "Ernesto", "lastName": "Valverde Tejedor", "shortFirstName": "Ernesto", "shortLastName": "Valverde", "type": "manager"}], "stat": [{"fh": "160", "sh": "173", "type": "accuratePass", "value": "333"}, {"fh": "3", "sh": "6", "type": "blockedScoringAtt", "value": "9"}, {"fh": "3", "sh": "3", "type": "cornerTaken", "value": "6"}, {"fh": "6", "sh": "8", "type": "fkFoulLost", "value": "14"}, {"fh": "6", "sh": "6", "type": "fkFoulWon", "value": "12"}, {"fh": "0", "sh": "1", "type": "goalAssist", "value": "1"}, {"fh": "1", "sh": "3", "type": "goalKicks", "value": "4"}, {"fh": "0", "sh": "1", "type": "goals", "value": "1"}, {"fh": "1", "sh": "0", "type": "goalsConceded", "value": "1"}, {"fh": "2", "sh": "1", "type": "lostCorners", "value": "3"}, {"fh": "0", "sh": "4", "type": "ontargetScoringAtt", "value": "4"}, {"fh": "51.1", "sh": "58.4", "type": "possessionPercentage", "value": "54.7"}, {"fh": "4", "sh": "0", "type": "saves", "value": "4"}, {"fh": "2", "sh": "4", "type": "shotOffTarget", "value": "6"}, {"fh": "0", "sh": "1", "type": "subsGoals", "value": "1"}, {"fh": "0", "sh": "5", "type": "subsMade", "value": "5"}, {"fh": "9", "sh": "4", "type": "totalClearance", "value": "13"}, {"fh": "2", "sh": "1", "type": "totalOffside", "value": "3"}, {"fh": "205", "sh": "216", "type": "totalPass", "value": "421"}, {"fh": "5", "sh": "14", "type": "totalScoringAtt", "value": "19"}, {"fh": "8", "sh": "5", "type": "totalTackle", "value": "13"}, {"fh": "10", "sh": "13", "type": "totalThrows", "value": "23"}, {"fh": "0", "sh": "4", "type": "totalYellowCard", "value": "4"}, {"fh": "3", "sh": "3", "type": "wonCorners", "value": "6"}, {"fh": "1", "sh": "5", "type": "wonTackle", "value": "6"}, {"type": "formationUsed", "value": "4231"}], "kit": {"id": "12043", "colour1": "#FF0000", "colour2": "#FFFFFF", "type": "home"}}, {"contestantId": "63f5h8t5e9qm1fqmvfkb23ghh", "formationUsed": "442", "averageAge": 25.9, "player": [{"playerId": "w503zyr8ipyobglth281uklx", "firstName": "Alejandro", "lastName": "Remiro Gargallo", "shortFirstName": "Álex", "shortLastName": "Remiro", "matchName": "Álex Remiro", "shirtNumber": 1, "position": "Goalkeeper", "positionSide": "Centre", "formationPlace": "1", "stat": [{"type": "accuratePass", "value": "21"}, {"type": "gameStarted", "value": "1"}, {"type": "goalKicks", "value": "7"}, {"type": "goalsConceded", "value": "1"}, {"type": "lostCorners", "value": "1"}, {"type": "minsPlayed", "value": "90"}, {"type": "saves", "value": "3"}, {"type": "totalClearance", "value": "3"}, {"type": "totalPass", "value": "44"}, {"type": "wasFouled", "value": "1"}, {"type": "formationPlace", "value": "1"}]}, {"playerId": "d4tdx2ctadv6kc3tbq4as8bmx", "firstName": "Sergio", "lastName": "Gómez Martín", "shortFirstName": "Sergio", "shortLastName": "Gómez", "matchName": "Sergio Gómez", "shirtNumber": 17, "position": "Defender", "positionSide": "Left", "formationPlace": "3", "stat": [{"type": "accuratePass", "value": "38"}, {"type": "cornerTaken", "value": "1"}, {"type": "fouls", "value": "1"}, {"type": "gameStarted", "value": "1"}, {"type": "goalAssist", "value": "1"}, {"type": "goalsConceded", "value": "1"}, {"type": "minsPlayed", "value": "90"}, {"type": "shotOffTarget", "value": "1"}, {"type": "totalClearance", "value": "5"}, {"type": "totalPass", "value": "46"}, {"type": "totalScoringAtt", "value": "1"}, {"type": "totalTackle", "value": "3"}, {"type": "totalThrows", "value": "8"}, {"type": "wasFouled", "value": "2"}, {"type": "wonCorners", "value": "2"}, {"type": "wonTackle", "value": "3"}, {"type": "formationPlace", "value": "3"}]}, {"playerId": "48gjuou5eashpj8wbwd18iju1", "firstName": "Igor", "lastName": "Zubeldia Elorza", "shortFirstName": "Igor", "shortLastName": "Zubeldia", "matchName": "Igor Zubeldia", "shirtNumber": 5, "position": "Defender", "positionSide": "Left/Centre", "formationPlace": "6", "stat": [{"type": "accuratePass", "value": "36"}, {"type": "fouls", "value": "4"}, {"type": "gameStarted", "value": "1"}, {"type": "goalKicks", "value": "5"}, {"type": "goalsConceded", "value": "1"}, {"type": "minsPlayed", "value": "90"}, {"type": "totalClearance", "value": "8"}, {"type": "totalPass", "value": "44"}, {"type": "totalTackle", "value": "4"}, {"type": "wonTackle", "value": "3"}, {"type": "yellowCard", "value": "1"}, {"type": "formationPlace", "value": "6"}]}, {"playerId": "8krgbfnydbtyongkwnsaj43kk", "firstName": "Jon", "lastName": "Martín Vicente", "shortFirstName": "Jon", "shortLastName": "Martín", "matchName": "Jon Martín", "shirtNumber": 31, "position": "Defender", "positionSide": "Centre/Right", "formationPlace": "5", "stat": [{"type": "accuratePass", "value": "29"}, {"type": "fouls", "value": "1"}, {"type": "gameStarted", "value": "1"}, {"type": "goalsConceded", "value": "1"}, {"type": "lostCorners", "value": "1"}, {"type": "minsPlayed", "value": "90"}, {"type": "ontargetScoringAtt", "value": "1"}, {"type": "totalClearance", "value": "13"}, {"type": "totalPass", "value": "30"}, {"type": "totalScoringAtt", "value": "1"}, {"type": "yellowCard", "value": "1"}, {"type": "formationPlace", "value": "5"}]}, {"playerId": "ezbplvktzcvzh5kwur32110mi", "firstName": "Jon Mikel", "lastName": "Aramburu Mejías", "shortFirstName": "Jon", "shortLastName": "Aramburu", "matchName": "J. Aramburu", "shirtNumber": 2, "position": "Defender", "positionSide": "Right", "formationPlace": "2", "stat": [{"type": "accuratePass", "value": "16"}, {"type": "fouls", "value": "2"}, {"type": "gameStarted", "value": "1"}, {"type": "goalsConceded", "value": "1"}, {"type": "minsPlayed", "value": "90"}, {"type": "totalClearance", "value": "6"}, {"type": "totalOffside", "value": "1"}, {"type": "totalPass", "value": "29"}, {"type": "totalTackle", "value": "9"}, {"type": "totalThrows", "value": "14"}, {"type": "wasFouled", "value": "3"}, {"type": "wonTackle", "value": "4"}, {"type": "formationPlace", "value": "2"}]}, {"playerId": "aka2yqxmqpioxc1qzkl62ejv8", "firstName": "Pablo", "lastName": "Marín Tejada", "shortFirstName": "Pablo", "shortLastName": "Marín", "matchName": "Pablo Marín", "shirtNumber": 15, "position": "Midfielder", "positionSide": "Left", "formationPlace": "11", "stat": [{"type": "accuratePass", "value": "11"}, {"type": "fouls", "value": "1"}, {"type": "gameStarted", "value": "1"}, {"type": "minsPlayed", "value": "85"}, {"type": "ontargetScoringAtt", "value": "1"}, {"type": "totalPass", "value": "14"}, {"type": "totalScoringAtt", "value": "1"}, {"type": "totalSubOff", "value": "1"}, {"type": "totalTackle", "value": "1"}, {"type": "wasFouled", "value": "1"}, {"type": "wonTackle", "value": "1"}, {"type": "formationPlace", "value": "11"}]}, {"playerId": "dsmcqfl0e1be4ag7czbnolo15", "firstName": "Carlos", "lastName": "Soler Barragán", "shortFirstName": "Carlos", "shortLastName": "Soler", "matchName": "Carlos Soler", "shirtNumber": 18, "position": "Midfielder", "positionSide": "Left/Centre", "formationPlace": "8", "stat": [{"type": "accuratePass", "value": "37"}, {"type": "cornerTaken", "value": "2"}, {"type": "fouls", "value": "1"}, {"type": "gameStarted", "value": "1"}, {"type": "goalsConceded", "value": "1"}, {"type": "lostCorners", "value": "2"}, {"type": "minsPlayed", "value": "90"}, {"type": "totalClearance", "value": "7"}, {"type": "totalPass", "value": "40"}, {"type": "totalTackle", "value": "2"}, {"type": "wasFouled", "value": "1"}, {"type": "formationPlace", "value": "8"}]}, {"playerId": "706la37b8u3v3n6mqtbjs73mc", "firstName": "Jon", "lastName": "Gorrotxategi Etxaniz", "shortFirstName": "Jon", "shortLastName": "Gorrotxategi", "matchName": "Jon Gorrotxategi", "shirtNumber": 4, "position": "Midfielder", "positionSide": "Centre/Right", "formationPlace": "4", "stat": [{"type": "accuratePass", "value": "25"}, {"type": "gameStarted", "value": "1"}, {"type": "minsPlayed", "value": "63"}, {"type": "totalClearance", "value": "3"}, {"type": "totalPass", "value": "31"}, {"type": "totalSubOff", "value": "1"}, {"type": "totalTackle", "value": "1"}, {"type": "wonTackle", "value": "1"}, {"type": "formationPlace", "value": "4"}]}, {"playerId": "7pmigpf4yfi6dfih8e1ogdwb9", "firstName": "Gonçalo Manuel", "lastName": "Ganchinho Guedes", "shortFirstName": "Gonçalo Manuel", "shortLastName": "Ganchinho Guedes", "knownName": "Gonçalo Guedes", "matchName": "Gonçalo Guedes", "shirtNumber": 11, "position": "Midfielder", "positionSide": "Right", "formationPlace": "7", "stat": [{"type": "accuratePass", "value": "12"}, {"type": "fouls", "value": "1"}, {"type": "gameStarted", "value": "1"}, {"type": "goals", "value": "1"}, {"type": "minsPlayed", "value": "77"}, {"type": "ontargetScoringAtt", "value": "3"}, {"type": "totalOffside", "value": "1"}, {"type": "totalPass", "value": "14"}, {"type": "totalScoringAtt", "value": "3"}, {"type": "totalSubOff", "value": "1"}, {"type": "totalTackle", "value": "3"}, {"type": "wasFouled", "value": "3"}, {"type": "wonCorners", "value": "1"}, {"type": "wonTackle", "value": "1"}, {"type": "formationPlace", "value": "7"}]}, {"playerId": "b45ryclny991bm7qosieyg1cl", "firstName": "Mikel", "lastName": "Oyarzabal Ugarte", "shortFirstName": "Mikel", "shortLastName": "Oyarzabal", "matchName": "Mikel Oyarzabal", "shirtNumber": 10, "position": "Striker", "positionSide": "Left/Centre", "formationPlace": "9", "captain": "yes", "stat": [{"type": "accuratePass", "value": "21"}, {"type": "fouls", "value": "1"}, {"type": "gameStarted", "value": "1"}, {"type": "minsPlayed", "value": "77"}, {"type": "ontargetScoringAtt", "value": "1"}, {"type": "shotOffTarget", "value": "1"}, {"type": "totalClearance", "value": "1"}, {"type": "totalOffside", "value": "1"}, {"type": "totalPass", "value": "25"}, {"type": "totalScoringAtt", "value": "2"}, {"type": "totalSubOff", "value": "1"}, {"type": "wasFouled", "value": "1"}, {"type": "formationPlace", "value": "9"}]}, {"playerId": "9x5uo2wkxp9fk1arygbkl6u0a", "firstName": "Luka", "lastName": "Sučić", "shortFirstName": "Luka", "shortLastName": "Sucic", "matchName": "L. Sučić", "shirtNumber": 24, "position": "Striker", "positionSide": "Centre/Right", "formationPlace": "10", "stat": [{"type": "accuratePass", "value": "8"}, {"type": "gameStarted", "value": "1"}, {"type": "lostCorners", "value": "2"}, {"type": "minsPlayed", "value": "63"}, {"type": "totalClearance", "value": "2"}, {"type": "totalOffside", "value": "1"}, {"type": "totalPass", "value": "15"}, {"type": "totalSubOff", "value": "1"}, {"type": "totalTackle", "value": "2"}, {"type": "wonTackle", "value": "1"}, {"type": "formationPlace", "value": "10"}]}, {"playerId": "2hqyw29ta24b0fk146a4mlf6c", "firstName": "Daniel", "lastName": "Díaz Gándara", "shortFirstName": "Daniel", "shortLastName": "Díaz", "matchName": "Dani Díaz", "shirtNumber": 26, "position": "Substitute", "subPosition": "Attacker", "stat": [{"type": "formationPlace", "value": "0"}]}, {"playerId": "e35v2pspdgl7t769d57e67ob9", "firstName": "Aritz", "lastName": "Elustondo Irribaria", "shortFirstName": "Aritz", "shortLastName": "Elustondo", "matchName": "Aritz Elustondo", "shirtNumber": 6, "position": "Substitute", "subPosition": "Defender", "stat": [{"type": "formationPlace", "value": "0"}]}, {"playerId": "29cp6coiba854vwntnzj5x1ck", "firstName": "Aitor", "lastName": "Fraga Torres", "shortFirstName": "Aitor", "shortLastName": "Fraga", "matchName": "Aitor Fraga", "shirtNumber": 32, "position": "Substitute", "subPosition": "Goalkeeper", "stat": [{"type": "formationPlace", "value": "0"}]}, {"playerId": "a5sz66h4t5kg1umvtth785jis", "firstName": "Wesley", "lastName": "Gassova Ribeiro Teixeira", "shortFirstName": "Wesley", "shortLastName": "Gassova Ribeiro Teixeira", "knownName": "Wesley", "matchName": "Wesley", "shirtNumber": 22, "position": "Substitute", "subPosition": "Attacker", "stat": [{"type": "accuratePass", "value": "3"}, {"type": "fouls", "value": "1"}, {"type": "goalsConceded", "value": "1"}, {"type": "minsPlayed", "value": "13"}, {"type": "totalClearance", "value": "1"}, {"type": "totalPass", "value": "6"}, {"type": "totalSubOn", "value": "1"}, {"type": "formationPlace", "value": "0"}]}, {"playerId": "c320492cbp1otejfp1i1oane1", "firstName": "Yangel Clemente", "lastName": "Herrera Ravelo", "shortFirstName": "Yangel", "shortLastName": "Herrera", "matchName": "Y. Herrera", "shirtNumber": 12, "position": "Substitute", "subPosition": "Midfielder", "stat": [{"type": "formationPlace", "value": "0"}]}, {"playerId": "dqiuqhsqsayvldfazfnp8d46i", "firstName": "Jon", "lastName": "Karrikaburu Jaimerena", "shortFirstName": "Jon", "shortLastName": "Karrikaburu", "matchName": "Jon Karrikaburu", "shirtNumber": 19, "position": "Substitute", "subPosition": "Attacker", "stat": [{"type": "formationPlace", "value": "0"}]}, {"playerId": "bj929w5yi7lnz36jxsi5qnq7e", "firstName": "Aihen", "lastName": "Muñoz Capellán", "shortFirstName": "Aihen", "shortLastName": "Muñoz", "matchName": "Aihen Muñoz", "shirtNumber": 3, "position": "Substitute", "subPosition": "Defender", "stat": [{"type": "goalsConceded", "value": "1"}, {"type": "minsPlayed", "value": "5"}, {"type": "totalClearance", "value": "3"}, {"type": "totalSubOn", "value": "1"}, {"type": "formationPlace", "value": "0"}]}, {"playerId": "dvrk8qmt9ta4c3kvjgsad7t91", "firstName": "Brais", "lastName": "Méndez Portela", "shortFirstName": "Brais", "shortLastName": "Méndez", "matchName": "Brais Méndez", "shirtNumber": 23, "position": "Substitute", "subPosition": "Midfielder", "stat": [{"type": "accuratePass", "value": "6"}, {"type": "fouls", "value": "1"}, {"type": "minsPlayed", "value": "20"}, {"type": "redCard", "value": "1"}, {"type": "totalPass", "value": "7"}, {"type": "totalSubOn", "value": "1"}, {"type": "totalTackle", "value": "2"}, {"type": "wonTackle", "value": "2"}, {"type": "formationPlace", "value": "0"}]}, {"playerId": "1fcmd6qaiira468e8mph4sis4", "firstName": "Job", "lastName": "Nguono Ochieng", "shortFirstName": "Job", "shortLastName": "Ochieng", "matchName": "J. Ochieng", "shirtNumber": 47, "position": "Substitute", "subPosition": "Attacker", "stat": [{"type": "formationPlace", "value": "0"}]}, {"playerId": "5nluxvc0wi0u1d5zcy7be5rkl", "firstName": "Álvaro", "lastName": "Odriozola Arzallus", "shortFirstName": "Álvaro", "shortLastName": "Odriozola", "matchName": "Álvaro Odriozola", "shirtNumber": 20, "position": "Substitute", "subPosition": "Defender", "stat": [{"type": "formationPlace", "value": "0"}]}, {"playerId": "et849xmcdgsy5itb8i4w7qkq2", "firstName": "Beñat", "lastName": "Turrientes Imaz", "shortFirstName": "Beñat", "shortLastName": "Turrientes", "matchName": "Beñat Turrientes", "shirtNumber": 8, "position": "Substitute", "subPosition": "Midfielder", "stat": [{"type": "accuratePass", "value": "9"}, {"type": "goalsConceded", "value": "1"}, {"type": "minsPlayed", "value": "27"}, {"type": "totalClearance", "value": "5"}, {"type": "totalPass", "value": "12"}, {"type": "totalSubOn", "value": "1"}, {"type": "totalTackle", "value": "2"}, {"type": "wasFouled", "value": "1"}, {"type": "wonTackle", "value": "1"}, {"type": "formationPlace", "value": "0"}]}, {"playerId": "euur9yvhgrieu4kl0vdkh244q", "firstName": "Orri Steinn", "lastName": "Óskarsson", "shortFirstName": "Orri", "shortLastName": "Óskarsson", "matchName": "O. Óskarsson", "shirtNumber": 9, "position": "Substitute", "subPosition": "Attacker", "stat": [{"type": "accuratePass", "value": "1"}, {"type": "goalsConceded", "value": "1"}, {"type": "minsPlayed", "value": "13"}, {"type": "totalClearance", "value": "1"}, {"type": "totalOffside", "value": "1"}, {"type": "totalPass", "value": "3"}, {"type": "totalSubOn", "value": "1"}, {"type": "formationPlace", "value": "0"}]}], "teamOfficial": [{"id": "b3tuy4l2g97qd67kz5pu5rp3p", "firstName": "Pellegrino", "lastName": "Matarazzo", "shortFirstName": "Pellegrino", "shortLastName": "Matarazzo", "type": "manager"}], "stat": [{"fh": "151", "sh": "122", "type": "accuratePass", "value": "273"}, {"fh": "2", "sh": "1", "type": "cornerTaken", "value": "3"}, {"fh": "6", "sh": "8", "type": "fkFoulLost", "value": "14"}, {"fh": "6", "sh": "7", "type": "fkFoulWon", "value": "13"}, {"fh": "1", "sh": "0", "type": "goalAssist", "value": "1"}, {"fh": "4", "sh": "8", "type": "goalKicks", "value": "12"}, {"fh": "1", "sh": "0", "type": "goals", "value": "1"}, {"fh": "0", "sh": "1", "type": "goalsConceded", "value": "1"}, {"fh": "3", "sh": "3", "type": "lostCorners", "value": "6"}, {"fh": "6", "sh": "0", "type": "ontargetScoringAtt", "value": "6"}, {"fh": "48.9", "sh": "41.6", "type": "possessionPercentage", "value": "45.3"}, {"fh": "0", "sh": "3", "type": "saves", "value": "3"}, {"fh": "0", "sh": "2", "type": "shotOffTarget", "value": "2"}, {"fh": "0", "sh": "5", "type": "subsMade", "value": "5"}, {"fh": "17", "sh": "41", "type": "totalClearance", "value": "58"}, {"fh": "3", "sh": "2", "type": "totalOffside", "value": "5"}, {"fh": "197", "sh": "163", "type": "totalPass", "value": "360"}, {"fh": "0", "sh": "1", "type": "totalRedCard", "value": "1"}, {"fh": "6", "sh": "2", "type": "totalScoringAtt", "value": "8"}, {"fh": "12", "sh": "17", "type": "totalTackle", "value": "29"}, {"fh": "12", "sh": "10", "type": "totalThrows", "value": "22"}, {"fh": "1", "sh": "1", "type": "totalYellowCard", "value": "2"}, {"fh": "2", "sh": "1", "type": "wonCorners", "value": "3"}, {"fh": "7", "sh": "10", "type": "wonTackle", "value": "17"}, {"type": "formationUsed", "value": "442"}], "kit": {"id": "25453", "colour1": "#FFFFFF", "colour2": "#0000FF", "type": "home"}}], "matchDetailsExtra": {"attendance": "48020", "matchOfficial": [{"id": "8wue7n8yhomnp6s0osmw9bqol", "type": "Main", "firstName": "Guillermo", "lastName": "Cuadra Fernández", "shortFirstName": "Guillermo", "shortLastName": "Cuadra Fernández"}, {"id": "1j9rafnjjytytg46t84j4p80l", "type": "Assistant referee 1", "firstName": "Guadalupe", "lastName": "Porras Ayuso", "shortFirstName": "Guadalupe", "shortLastName": "Porras Ayuso"}, {"id": "7yjiy5gff2qpdkcqi824hqyju", "type": "Assistant referee 2", "firstName": "Alejandro", "lastName": "Estévez Iglesias", "shortFirstName": "Alejandro", "shortLastName": "Estevez Iglesias"}, {"id": "9kmm4udukqe341q1wg5vjx3vt", "type": "Fourth official", "firstName": "Imanol", "lastName": "Irurtzun Artola", "shortFirstName": "Imanol", "shortLastName": "Irurtzun Artola"}, {"id": "37u09m3xbwx9v4p9ybc5xg2c5", "type": "Video Assistant Referee", "firstName": "Carlos", "lastName": "del Cerro Grande", "shortFirstName": "Carlos", "shortLastName": "del Cerro Grande"}, {"id": "2ic967kwl63hknm64rrewzmj9", "type": "Assistant VAR Official", "firstName": "Valentín", "lastName": "Pizarro Gómez", "shortFirstName": "Valentín", "shortLastName": "Pizarro Gómez"}]}}}